README.md
setup.py
ex_package/__init__.py
ex_package/numpy_function.py
ex_package_JStox.egg-info/PKG-INFO
ex_package_JStox.egg-info/SOURCES.txt
ex_package_JStox.egg-info/dependency_links.txt
ex_package_JStox.egg-info/requires.txt
ex_package_JStox.egg-info/top_level.txt